a_pandas_ex_excel_edit/README.MD
a_pandas_ex_excel_edit/__init__.py
a_pandas_ex_excel_edit/requirements.txt
a_pandas_ex_excel_edit/thirdparty.json
a_pandas_ex_excel_edit-0.11.dist-info/LICENSE.rst
a_pandas_ex_excel_edit-0.11.dist-info/METADATA
a_pandas_ex_excel_edit-0.11.dist-info/WHEEL
a_pandas_ex_excel_edit-0.11.dist-info/top_level.txt
a_pandas_ex_excel_edit-0.11.dist-info/RECORD
