Metadata-Version: 2.1
Name: a-pandas-ex-excel-edit
Version: 0.11
Summary: If you have to change a lot of arbitrary values which don't have a clear pattern, use Excel!
Home-page: https://github.com/hansalemaos/a_pandas_ex_excel_edit
Author: Johannes Fischer
Author-email: aulasparticularesdealemaosp@gmail.com
License: MIT
Keywords: pandas,excel,MS Excel,quick,edit
Classifier: Development Status :: 4 - Beta
Classifier: Programming Language :: Python :: 3 :: Only
Classifier: Programming Language :: Python :: 3.10
Classifier: Topic :: Software Development :: Libraries :: Python Modules
Classifier: Topic :: Utilities
License-File: LICENSE.rst
Requires-Dist: pandas
